CHANGES.txt
LICENSE.txt
MANIFEST.in
README.txt
setup.py
js/__init__.py
js.icanhaz.egg-info/PKG-INFO
js.icanhaz.egg-info/SOURCES.txt
js.icanhaz.egg-info/dependency_links.txt
js.icanhaz.egg-info/entry_points.txt
js.icanhaz.egg-info/namespace_packages.txt
js.icanhaz.egg-info/not-zip-safe
js.icanhaz.egg-info/requires.txt
js.icanhaz.egg-info/top_level.txt
js/icanhaz/__init__.py
js/icanhaz/test_icanhaz.js.txt
js/icanhaz/resources/.git
js/icanhaz/resources/.gitignore
js/icanhaz/resources/.gitmodules
js/icanhaz/resources/ICanHaz-no-mustache.js
js/icanhaz/resources/ICanHaz-no-mustache.min.js
js/icanhaz/resources/ICanHaz.js
js/icanhaz/resources/ICanHaz.min.js
js/icanhaz/resources/component.json
js/icanhaz/resources/demo.html
js/icanhaz/resources/package.json
js/icanhaz/resources/version.txt
js/icanhaz/resources/source/intro.js
js/icanhaz/resources/source/main.js
js/icanhaz/resources/test/ich_test.js
js/icanhaz/resources/test/jquery-1.4.4.min.js
js/icanhaz/resources/test/jquery-1.9.1.min.js
js/icanhaz/resources/test/node_test.js
js/icanhaz/resources/test/test-jquery-1.9.1.html
js/icanhaz/resources/test/test-jquery.html
js/icanhaz/resources/test/test-no-mustache.html
js/icanhaz/resources/test/test-zepto.html
js/icanhaz/resources/test/test.html
js/icanhaz/resources/test/zepto.min.js
js/icanhaz/resources/test/qunit/qunit.css
js/icanhaz/resources/test/qunit/qunit.js