Metadata-Version: 1.0
Name: js.icanhaz
Version: 0.10.3
Summary: Fanstatic packaging of ICanHaz.js
Home-page: https://github.com/dnozay/js.ICanHaz
Author: Damien Nozay
Author-email: damien.nozay@gmail.com
License: BSD
Platform: UNKNOWN
